pypolys/__init__.py
pypolys/factory.py
pypolys/mpolys.py
pypolys/polys.py
pypolys/test_factory.py
pypolys/test_mpolys.py
pypolys/test_polys.py
pypolys/tester1.py
pypolys-0.2.0.dist-info/LICENSE
pypolys-0.2.0.dist-info/METADATA
pypolys-0.2.0.dist-info/WHEEL
pypolys-0.2.0.dist-info/top_level.txt
pypolys-0.2.0.dist-info/RECORD
