Metadata-Version: 2.1
Name: pypolys
Version: 0.2.0
Summary: Python implementation of polynomials
Home-page: https://github.com/ufkapano/pypolys
Author: Andrzej Kapanowski
Author-email: andrzej.kapanowski@uj.edu.pl
License: UNKNOWN
Platform: UNKNOWN
Classifier: Programming Language :: Python :: 3
Classifier: License :: OSI Approved :: BSD License
Classifier: Operating System :: OS Independent
Classifier: Topic :: Education
Classifier: Topic :: Scientific/Engineering
Requires-Python: >=3.7
License-File: LICENSE
